[{
		"id": "59b6bb030012f61854b35938",
		"name": "allium",
		"buyPierre": "30",
		"buyJoja": "37",
		"saleRegular": "50",
		"saleSilver": "62",
		"saleGold": "75",
		"growing": "7",
		"produce": null,
		"multip": null,
		"img": "Blue_Jazz.png",
		"season": "primavera"
	}, {
		"id": "59b6bb030012f61854b35939",
		"name": "coliflor",
		"buyPierre": "80",
		"buyJoja": "100",
		"saleRegular": "175",
		"saleSilver": "218",
		"saleGold": "262",
		"growing": "12",
		"produce": null,
		"multip": null,
		"img": "Cauliflower.png",
		"season": "primavera"
	}, {
		"id": "59b6bb030012f61854b3593a",
		"name": "café",
		"buyPierre": "2500",
		"buyJoja": null,
		"saleRegular": "15",
		"saleSilver": "18",
		"saleGold": "22",
		"growing": "10",
		"produce": "2",
		"multip": null,
		"img": "Coffee_Bean.png",
		"season": "primavera"
	}, {
		"id": "59b6bb030012f61854b3593b",
		"name": "ajo",
		"buyPierre": "40",
		"buyJoja": null,
		"saleRegular": "60",
		"saleSilver": "75",
		"saleGold": "90",
		"growing": "4",
		"produce": null,
		"multip": null,
		"img": "Garlic.png",
		"season": "primavera"
	}, {
		"id": "59b6bb030012f61854b3593c",
		"name": "judías",
		"buyPierre": "60",
		"buyJoja": "75",
		"saleRegular": "40",
		"saleSilver": "50",
		"saleGold": "60",
		"growing": "10",
		"produce": "3",
		"multip": null,
		"img": "Green_Bean.png",
		"season": "primavera"
	}, {
		"id": "59b6bb030012f61854b3593d",
		"name": "col rizada",
		"buyPierre": "70",
		"buyJoja": "87",
		"saleRegular": "110",
		"saleSilver": "137",
		"saleGold": "165",
		"growing": "6",
		"produce": null,
		"multip": null,
		"img": "Kale.png",
		"season": "primavera"
	}, {
		"id": "59b6bb030012f61854b3593e",
		"name": "chirivía",
		"buyPierre": "20",
		"buyJoja": "25",
		"saleRegular": "35",
		"saleSilver": "43",
		"saleGold": "52",
		"growing": "4",
		"produce": null,
		"multip": null,
		"img": "Parsnip.png",
		"season": "primavera"
	}, {
		"id": "59b6bb030012f61854b3593f",
		"name": "patata",
		"buyPierre": "50",
		"buyJoja": "62",
		"saleRegular": "80",
		"saleSilver": "100",
		"saleGold": "120",
		"growing": "6",
		"produce": null,
		"multip": null,
		"img": "Potato.png",
		"season": "primavera"
	}, {
		"id": "59b6bb030012f61854b35940",
		"name": "ruibarbo",
		"buyPierre": "100",
		"buyJoja": null,
		"saleRegular": "220",
		"saleSilver": "275",
		"saleGold": "330",
		"growing": "13",
		"produce": null,
		"multip": null,
		"img": "Rhubarb.png",
		"season": "primavera"
	}, {
		"id": "59b6bb030012f61854b35941",
		"name": "fresa",
		"buyPierre": "100",
		"buyJoja": null,
		"saleRegular": "120",
		"saleSilver": "150",
		"saleGold": "180",
		"growing": "8",
		"produce": "4",
		"multip": null,
		"img": "Strawberry.png",
		"season": "primavera"
	}, {
		"id": "59b6bb030012f61854b35942",
		"name": "tulipán",
		"buyPierre": "20",
		"buyJoja": "25",
		"saleRegular": "30",
		"saleSilver": "37",
		"saleGold": "45",
		"growing": "6",
		"produce": null,
		"multip": null,
		"img": "Tulip.png",
		"season": "primavera"
	}, {
		"id": "59b6bb030012f61854b35943",
		"name": "arándano",
		"buyPierre": "80",
		"buyJoja": null,
		"saleRegular": "50",
		"saleSilver": "62",
		"saleGold": "75",
		"growing": "13",
		"produce": "4",
		"multip": "3",
		"img": "Blueberry.png",
		"season": "verano"
	}, {
		"id": "59b6bb030012f61854b35944",
		"name": "maíz",
		"buyPierre": "150",
		"buyJoja": "187",
		"saleRegular": "50",
		"saleSilver": "62",
		"saleGold": "75",
		"growing": "14",
		"produce": "4",
		"multip": null,
		"img": "Corn.png",
		"season": "verano,otonio"
	}, {
		"id": "59b6bb030012f61854b35945",
		"name": "lúpulos",
		"buyPierre": "60",
		"buyJoja": "75",
		"saleRegular": "25",
		"saleSilver": "31",
		"saleGold": "37",
		"growing": "11",
		"produce": "1",
		"multip": null,
		"img": "Hops.png",
		"season": "verano"
	}, {
		"id": "59b6bb030012f61854b35946",
		"name": "chile",
		"buyPierre": "40",
		"buyJoja": "50",
		"saleRegular": "40",
		"saleSilver": "50",
		"saleGold": "60",
		"growing": "5",
		"produce": "3",
		"multip": null,
		"img": "Hot_Pepper.png",
		"season": "verano"
	}, {
		"id": "59b6bb030012f61854b35947",
		"name": "melón",
		"buyPierre": "80",
		"buyJoja": "100",
		"saleRegular": "250",
		"saleSilver": "312",
		"saleGold": "375",
		"growing": "12",
		"produce": null,
		"multip": null,
		"img": "Melon.png",
		"season": "verano"
	}, {
		"id": "59b6bb030012f61854b35948",
		"name": "amapola",
		"buyPierre": "100",
		"buyJoja": "125",
		"saleRegular": "140",
		"saleSilver": "175",
		"saleGold": "210",
		"growing": "7",
		"produce": null,
		"multip": null,
		"img": "Poppy.png",
		"season": "verano"
	}, {
		"id": "59b6bb030012f61854b35949",
		"name": "rábano",
		"buyPierre": "40",
		"buyJoja": "50",
		"saleRegular": "90",
		"saleSilver": "112",
		"saleGold": "135",
		"growing": "6",
		"produce": null,
		"multip": null,
		"img": "Radish.png",
		"season": "verano"
	}, {
		"id": "59b6bb030012f61854b3594a",
		"name": "lombarda",
		"buyPierre": "100",
		"buyJoja": null,
		"saleRegular": "260",
		"saleSilver": "325",
		"saleGold": "390",
		"growing": "9",
		"produce": null,
		"multip": null,
		"img": "Red_Cabbage.png",
		"season": "verano"
	}, {
		"id": "59b6bb030012f61854b3594b",
		"name": "carambola",
		"buyPierre": "400",
		"buyJoja": null,
		"saleRegular": "750",
		"saleSilver": "937",
		"saleGold": "1125",
		"growing": "13",
		"produce": null,
		"multip": null,
		"img": "Starfruit.png",
		"season": "verano"
	}, {
		"id": "59b6bb030012f61854b3594c",
		"name": "lentejuela",
		"buyPierre": "50",
		"buyJoja": "62",
		"saleRegular": "90",
		"saleSilver": "112",
		"saleGold": "135",
		"growing": "8",
		"produce": null,
		"multip": null,
		"img": "Summer_Spangle.png",
		"season": "verano"
	}, {
		"id": "59b6bb030012f61854b3594d",
		"name": "girasol",
		"buyPierre": "200",
		"buyJoja": "125",
		"saleRegular": "80",
		"saleSilver": "100",
		"saleGold": "120",
		"growing": "8",
		"produce": null,
		"multip": null,
		"img": "Sunflower.png",
		"season": "verano,otonio"
	}, {
		"id": "59b6bb030012f61854b3594e",
		"name": "tomate",
		"buyPierre": "50",
		"buyJoja": "62",
		"saleRegular": "60",
		"saleSilver": "75",
		"saleGold": "90",
		"growing": "11",
		"produce": "4",
		"multip": null,
		"img": "Tomato.png",
		"season": "verano"
	}, {
		"id": "59b6bb030012f61854b3594f",
		"name": "trigo",
		"buyPierre": "10",
		"buyJoja": "12",
		"saleRegular": "25",
		"saleSilver": "31",
		"saleGold": "37",
		"growing": "4",
		"produce": null,
		"multip": null,
		"img": "Wheat.png",
		"season": "verano,otonio"
	}, {
		"id": "59b6bb030012f61854b35950",
		"name": "amaranto",
		"buyPierre": "70",
		"buyJoja": "87",
		"saleRegular": "150",
		"saleSilver": "187",
		"saleGold": "225",
		"growing": "7",
		"produce": null,
		"multip": null,
		"img": "Amaranth.png",
		"season": "otonio"
	}, {
		"id": "59b6bb030012f61854b35951",
		"name": "alcachofa",
		"buyPierre": "30",
		"buyJoja": null,
		"saleRegular": "160",
		"saleSilver": "200",
		"saleGold": "240",
		"growing": "8",
		"produce": null,
		"multip": null,
		"img": "Artichoke.png",
		"season": "otonio"
	}, {
		"id": "59b6bb030012f61854b35952",
		"name": "remolacha",
		"buyPierre": "20",
		"buyJoja": null,
		"saleRegular": "100",
		"saleSilver": "125",
		"saleGold": "150",
		"growing": "6",
		"produce": null,
		"multip": null,
		"img": "Beet.png",
		"season": "otonio"
	}, {
		"id": "59b6bb030012f61854b35953",
		"name": "col china",
		"buyPierre": "50",
		"buyJoja": "62",
		"saleRegular": "80",
		"saleSilver": "100",
		"saleGold": "120",
		"growing": "4",
		"produce": null,
		"multip": null,
		"img": "Bok_Choy.png",
		"season": "otonio"
	}, {
		"id": "59b6bb030012f61854b35954",
		"name": "grosella",
		"buyPierre": "240",
		"buyJoja": "300",
		"saleRegular": "75",
		"saleSilver": "93",
		"saleGold": "112",
		"growing": "7",
		"produce": "5",
		"multip": "2",
		"img": "Cranberries.png",
		"season": "otonio"
	}, {
		"id": "59b6bb030012f61854b35955",
		"name": "berenjena",
		"buyPierre": "20",
		"buyJoja": "25",
		"saleRegular": "60",
		"saleSilver": "75",
		"saleGold": "90",
		"growing": "5",
		"produce": "5",
		"multip": null,
		"img": "Eggplant.png",
		"season": "otonio"
	}, {
		"id": "59b6bb030012f61854b35956",
		"name": "hada",
		"buyPierre": "200",
		"buyJoja": "250",
		"saleRegular": "290",
		"saleSilver": "362",
		"saleGold": "435",
		"growing": "12",
		"produce": null,
		"multip": null,
		"img": "Fairy_Rose.png",
		"season": "otonio"
	}, {
		"id": "59b6bb030012f61854b35957",
		"name": "uvas",
		"buyPierre": "60",
		"buyJoja": "75",
		"saleRegular": "80",
		"saleSilver": "100",
		"saleGold": "120",
		"growing": "10",
		"produce": "3",
		"multip": null,
		"img": "Grape.png",
		"season": "otonio"
	}, {
		"id": "59b6bb030012f61854b35958",
		"name": "calabaza",
		"buyPierre": "100",
		"buyJoja": "125",
		"saleRegular": "320",
		"saleSilver": "400",
		"saleGold": "480",
		"growing": "13",
		"produce": null,
		"multip": null,
		"img": "Pumpkin.png",
		"season": "otonio"
	}, {
		"id": "59b6bb030012f61854b35959",
		"name": "ñame",
		"buyPierre": "60",
		"buyJoja": "75",
		"saleRegular": "160",
		"saleSilver": "200",
		"saleGold": "240",
		"growing": "10",
		"produce": null,
		"multip": null,
		"img": "Yam.png",
		"season": "otonio"
	}, {
		"id": "59b6bb030012f61854b3595a",
		"name": "rara",
		"buyPierre": "1000",
		"buyJoja": null,
		"saleRegular": "3000",
		"saleSilver": "3750",
		"saleGold": "4500",
		"growing": "24",
		"produce": null,
		"multip": null,
		"img": "Sweet_Gem_Berry.png",
		"season": "otonio"
	}, {
		"id": "59b6bb030012f61854b3595b",
		"name": "milenarias",
		"buyPierre": null,
		"buyJoja": null,
		"saleRegular": "550",
		"saleSilver": "687",
		"saleGold": "825",
		"growing": "28",
		"produce": "7",
		"multip": null,
		"img": "Beet.png",
		"season": "primave,verano,otonio"
	}
]
